MANIFEST.in
README.rst
setup.py
openstack/__init__.py
openstack/nose_plugin.py
openstack.nose_plugin.egg-info/PKG-INFO
openstack.nose_plugin.egg-info/SOURCES.txt
openstack.nose_plugin.egg-info/dependency_links.txt
openstack.nose_plugin.egg-info/entry_points.txt
openstack.nose_plugin.egg-info/requires.txt
openstack.nose_plugin.egg-info/top_level.txt