Metadata-Version: 1.0
Name: openstack.nose-plugin
Version: 0.4
Summary: openstack run_tests.py style output for nosetests
Home-page: https://github.com/jkoelker/openstack-nose
Author: Jason Kölker
Author-email: jason@koelker.net
License: Apache Software License
Keywords: nose
Platform: UNKNOWN
